herkules/Herkules.py
herkules/HerkulesTypes.py
herkules/__init__.py
herkules/py.typed
herkules-1.2.2.dist-info/METADATA
herkules-1.2.2.dist-info/WHEEL
herkules-1.2.2.dist-info/entry_points.txt
herkules-1.2.2.dist-info/licenses/LICENSE.md
herkules-1.2.2.dist-info/RECORD
