Metadata-Version: 2.4
Name: Herkules
Version: 1.2.2
Summary: Crawl directories with style
Project-URL: Homepage, https://github.com/mzuther/Herkules
Project-URL: Repository, https://github.com/mzuther/Herkules.git
Project-URL: Changelog, https://github.com/mzuther/Herkules/blob/main/CHANGELOG.md
Author-email: Martin Zuther <code@mzuther.de>
License-Expression: BSD-3-Clause
License-File: LICENSE.md
Keywords: file search,pure,simple
Classifier: Development Status :: 5 - Production/Stable
Classifier: Environment :: Console
Classifier: Intended Audience :: Developers
Classifier: License :: OSI Approved :: BSD License
Classifier: Operating System :: OS Independent
Classifier: Programming Language :: Python :: 3
Classifier: Programming Language :: Python :: 3.10
Classifier: Programming Language :: Python :: 3.11
Classifier: Programming Language :: Python :: 3.12
Classifier: Programming Language :: Python :: 3.13
Classifier: Programming Language :: Python :: 3.14
Classifier: Topic :: Utilities
Classifier: Typing :: Typed
Requires-Python: <4.0,>=3.10
